tbase_theme_tailwind/__init__.py
tbase_theme_tailwind/admin.py
tbase_theme_tailwind/apps.py
tbase_theme_tailwind/models.py
tbase_theme_tailwind/tests.py
tbase_theme_tailwind/views.py
tbase_theme_tailwind/__pycache__/__init__.cpython-310.pyc
tbase_theme_tailwind/__pycache__/admin.cpython-310.pyc
tbase_theme_tailwind/__pycache__/apps.cpython-310.pyc
tbase_theme_tailwind/__pycache__/models.cpython-310.pyc
tbase_theme_tailwind/migrations/__init__.py
tbase_theme_tailwind/static/agency_and_startup/bundle.js
tbase_theme_tailwind/static/agency_and_startup/bundle.js:Zone.Identifier
tbase_theme_tailwind/static/agency_and_startup/favicon.ico
tbase_theme_tailwind/static/agency_and_startup/favicon.ico:Zone.Identifier
tbase_theme_tailwind/static/agency_and_startup/style.css
tbase_theme_tailwind/static/agency_and_startup/style.css:Zone.Identifier
tbase_theme_tailwind/static/agency_and_startup/images/404.svg
tbase_theme_tailwind/static/agency_and_startup/images/404.svg:Zone.Identifier
tbase_theme_tailwind/static/agency_and_startup/images/about-01.png
tbase_theme_tailwind/static/agency_and_startup/images/about-01.png:Zone.Identifier
tbase_theme_tailwind/static/agency_and_startup/images/about-02.png
tbase_theme_tailwind/static/agency_and_startup/images/about-02.png:Zone.Identifier
tbase_theme_tailwind/static/agency_and_startup/images/about-03.png
tbase_theme_tailwind/static/agency_and_startup/images/about-03.png:Zone.Identifier
tbase_theme_tailwind/static/agency_and_startup/images/blog-01.png
tbase_theme_tailwind/static/agency_and_startup/images/blog-01.png:Zone.Identifier
tbase_theme_tailwind/static/agency_and_startup/images/blog-02.png
tbase_theme_tailwind/static/agency_and_startup/images/blog-02.png:Zone.Identifier
tbase_theme_tailwind/static/agency_and_startup/images/blog-03.png
tbase_theme_tailwind/static/agency_and_startup/images/blog-03.png:Zone.Identifier
tbase_theme_tailwind/static/agency_and_startup/images/blog-04.png
django_tbase_theme_tailwind-2023.7.316883187.dist-info/METADATA
django_tbase_theme_tailwind-2023.7.316883187.dist-info/WHEEL
django_tbase_theme_tailwind-2023.7.316883187.dist-info/top_level.txt
django_tbase_theme_tailwind-2023.7.316883187.dist-info/RECORD
