Metadata-Version: 2.1
Name: django-tbase-theme-tailwind
Version: 2023.7.316883187
Summary: Terry django base post ,
Home-page: https://terrychanorg.jetbrains.space/p/django-expand/repositories/tbase_theme_tailwind/files/README.md
Author: Terry Chan
Author-email: napoler2008@gmail.com
Requires-Dist: django-sitetree (==1.17.2)
